gomory_hu/__init__.py
python_GomoryHu-1.0.dist-info/METADATA
python_GomoryHu-1.0.dist-info/RECORD
python_GomoryHu-1.0.dist-info/WHEEL
python_GomoryHu-1.0.dist-info/top_level.txt
