Metadata-Version: 2.1
Name: python-GomoryHu
Version: 1.0
Summary: Gomory-Hu tree Data Structure Algorithm for Python with Gusfield Algorithm
Home-page: https://github.com/papachristoumarios/python-GomoryHu
Author: Marios Papachristou
Author-email: papachristoumarios@gmail.com
License: UNKNOWN
Platform: UNKNOWN
